{
  "5892f329-0047-4508-b48a-c024106241fd:bob@example.com": {
    "clubId": "5892f329-0047-4508-b48a-c024106241fd",
    "email": "bob@example.com",
    "invitedBy": "local-user",
    "status": "pending",
    "createdAt": "2026-05-07T10:00:00.000Z"
  },
  "5892f329-0047-4508-b48a-c024106241fd:alice@example.com": {
    "clubId": "5892f329-0047-4508-b48a-c024106241fd",
    "email": "alice@example.com",
    "invitedBy": "local-user",
    "status": "pending",
    "createdAt": "2026-05-07T10:05:00.000Z"
  },
  "5892f329-0047-4508-b48a-c024106241fd:newmember@example.com": {
    "clubId": "5892f329-0047-4508-b48a-c024106241fd",
    "email": "newmember@example.com",
    "invitedBy": "local-user",
    "status": "pending",
    "createdAt": "2026-05-07T10:10:00.000Z"
  },
  "5892f329-0047-4508-b48a-c024106241fd:friend@gmail.com": {
    "clubId": "5892f329-0047-4508-b48a-c024106241fd",
    "email": "friend@gmail.com",
    "invitedBy": "local-user",
    "status": "pending",
    "createdAt": "2026-05-07T10:15:00.000Z"
  }
}
